raysect/__init__.py
raysect/_version.py
raysect/core/__init__.pxd
raysect/core/__init__.py
raysect/core/boundingbox.cpython-312-x86_64-linux-musl.so
raysect/core/boundingbox.pxd
raysect/core/boundingsphere.cpython-312-x86_64-linux-musl.so
raysect/core/boundingsphere.pxd
raysect/core/constants.py
raysect/core/containers.cpython-312-x86_64-linux-musl.so
raysect/core/containers.pxd
raysect/core/intersection.cpython-312-x86_64-linux-musl.so
raysect/core/intersection.pxd
raysect/core/material.cpython-312-x86_64-linux-musl.so
raysect/core/material.pxd
raysect/core/ray.cpython-312-x86_64-linux-musl.so
raysect/core/ray.pxd
raysect/core/workflow.py
raysect/core/acceleration/__init__.pxd
raysect/core/acceleration/__init__.py
raysect/core/acceleration/accelerator.cpython-312-x86_64-linux-musl.so
raysect/core/acceleration/accelerator.pxd
raysect/core/acceleration/boundprimitive.cpython-312-x86_64-linux-musl.so
raysect/core/acceleration/boundprimitive.pxd
raysect/core/acceleration/kdtree.cpython-312-x86_64-linux-musl.so
raysect/core/acceleration/kdtree.pxd
raysect/core/acceleration/unaccelerated.cpython-312-x86_64-linux-musl.so
raysect/core/acceleration/unaccelerated.pxd
raysect/core/acceleration/tests/__init__.py
raysect/core/math/__init__.pxd
raysect/core/math/__init__.py
raysect/core/math/_mat4.cpython-312-x86_64-linux-musl.so
raysect/core/math/_mat4.pxd
raysect/core/math/_vec3.cpython-312-x86_64-linux-musl.so
raysect/core/math/_vec3.pxd
raysect/core/math/affinematrix.cpython-312-x86_64-linux-musl.so
raysect/core/math/affinematrix.pxd
raysect/core/math/normal.cpython-312-x86_64-linux-musl.so
raysect/core/math/normal.pxd
raysect/core/math/point.cpython-312-x86_64-linux-musl.so
raysect/core/math/point.pxd
raysect/core/math/polygon.cpython-312-x86_64-linux-musl.so
raysect/core/math/polygon.pxd
raysect/core/math/quaternion.cpython-312-x86_64-linux-musl.so
raysect/core/math/quaternion.pxd
raysect-0.9.0.dist-info/METADATA
raysect-0.9.0.dist-info/WHEEL
raysect-0.9.0.dist-info/RECORD
raysect-0.9.0.dist-info/licenses/LICENSE.txt
