Metadata-Version: 2.4
Name: raysect
Version: 0.9.0
Summary: A Ray-tracing Framework for Science and Engineering
Author-Email: "Dr Alex Meakins et al." <developers@raysect.org>
License-Expression: BSD-3-Clause
License-File: LICENSE.txt
Classifier: Development Status :: 5 - Production/Stable
Classifier: Intended Audience :: Science/Research
Classifier: Intended Audience :: Education
Classifier: Intended Audience :: Developers
Classifier: Natural Language :: English
Classifier: Operating System :: POSIX :: Linux
Classifier: Programming Language :: Cython
Classifier: Programming Language :: Python :: 3
Classifier: Topic :: Multimedia :: Graphics :: 3D Rendering
Classifier: Topic :: Scientific/Engineering :: Physics
Project-URL: Homepage, https://www.raysect.org
Project-URL: Repository, https://github.com/raysect/source
Project-URL: Issues, https://github.com/raysect/source/issues
Project-URL: Changelog, https://github.com/raysect/source/blob/master/CHANGELOG.txt
Requires-Python: >=3.9
Requires-Dist: numpy>=2
Requires-Dist: matplotlib
